glicid_spawner/__init__.py
glicid_spawner/form.py
glicid_spawner/micromamba.py
glicid_spawner/progress.py
glicid_spawner/resources.py
glicid_spawner/singleuser.py
glicid_spawner/slurm.py
glicid_spawner/spawner.py
glicid_spawner/templates/slurm_script.jinja
glicid_spawner/templates/spawner_form.jinja
glicid_spawner/templates/static/style.css
glicid_spawner/templates/views/chdir.jinja
glicid_spawner/templates/views/envs.jinja
glicid_spawner/templates/views/resources.jinja
glicid_spawner/templates/views/slurm.jinja
glicid_spawner/templates/views/username.jinja
glicid_spawner/templates.py
glicid_spawner-1.2.dist-info/LICENSE.md
glicid_spawner-1.2.dist-info/METADATA
glicid_spawner-1.2.dist-info/WHEEL
glicid_spawner-1.2.dist-info/entry_points.txt
glicid_spawner-1.2.dist-info/RECORD
