Metadata-Version: 2.1
Name: glicid-spawner
Version: 1.2
Summary: JupyterHub Batch Spawner for GLiCID
Home-page: https://gitlab.univ-nantes.fr/glicid/jupyter/spawner
License: BSD 3-Clause License
Author: Benoit Seignovert
Author-email: benoit.seignovert@univ-nantes.fr
Requires-Python: >=3.10,<4.0
Classifier: License :: Other/Proprietary License
Classifier: Programming Language :: Python :: 3
Classifier: Programming Language :: Python :: 3.10
Classifier: Programming Language :: Python :: 3.11
Classifier: Programming Language :: Python :: 3.12
Requires-Dist: batchspawner (>=1.3.0,<2.0.0)
Requires-Dist: jinja2 (>=3.1.3,<4.0.0)
Requires-Dist: jupyterhub (>=4.0,<5.0)
Project-URL: Repository, https://gitlab.univ-nantes.fr/glicid/jupyter/spawner
